{
	"info": {
		"_postman_id": "9c5f7cf3-70f2-4467-8d98-7f8b27633278",
		"name": "Editorial Tests",
		"description": "Colección de pruebas sobre el recurso Editorial",
		"schema": "https://schema.getpostman.com/json/collection/v2.1.0/collection.json",
		"_exporter_id": "25917437"
	},
	"item": [
		{
			"name": "Crear una editorial",
			"event": [
				{
					"listen": "test",
					"script": {
						"exec": [
							"var data = JSON.parse(responseBody);",
							"postman.setGlobalVariable(\"editorial_id_1\",data.id);",
							"tests[\"no genera error en el Post\"] = responseCode.code === 201;"
						],
						"type": "text/javascript"
					}
				}
			],
			"request": {
				"method": "POST",
				"header": [
					{
						"key": "Content-Type",
						"value": "application/json"
					}
				],
				"body": {
					"mode": "raw",
					"raw": "{\n    \"name\": \"Norma\"\n}"
				},
				"url": {
					"raw": "{{baseUrl}}/editorials",
					"host": [
						"{{baseUrl}}"
					],
					"path": [
						"editorials"
					]
				},
				"description": "**Release: Paso-5**\r\n\r\nCrea una nueva editorial. El recurso solo tiene de atributo \"name\" que debe ser único. El Id es inicializado por la BD y se debe ver en la respuesta. \r\n\r\nPara la prueba, se guarda el id en una variable que será utilizada en otras peticiones de la colección.\r\n\r\n**Código http esperado: 200**"
			},
			"response": []
		},
		{
			"name": "Crear una editorial 2",
			"event": [
				{
					"listen": "test",
					"script": {
						"exec": [
							"var data = JSON.parse(responseBody);",
							"postman.setGlobalVariable(\"editorial_id_2\",data.id);",
							"tests[\"no genera error en el Post\"] = responseCode.code === 201;",
							"console.log(data.id);",
							""
						],
						"type": "text/javascript"
					}
				}
			],
			"request": {
				"method": "POST",
				"header": [
					{
						"key": "Content-Type",
						"value": "application/json"
					}
				],
				"body": {
					"mode": "raw",
					"raw": "{\n    \"name\": \"Planeta\"\n}"
				},
				"url": {
					"raw": "{{baseUrl}}/editorials",
					"host": [
						"{{baseUrl}}"
					],
					"path": [
						"editorials"
					]
				},
				"description": "**Release: Paso-5**\r\n\r\nCrea otra editorial. El recurso solo tiene de atributo \"name\" que debe ser único. El Id es inicializado por la BD y se debe ver en la respuesta. \r\n\r\nEsta segunda editorial se utiliza para probar la petición que consultar todas las editoriales\r\n\r\nPara la prueba, se guarda el id en una variable que será utilizada en otras peticiones de la colección.\r\n\r\n**Código http esperado: 200**"
			},
			"response": []
		},
		{
			"name": "Crear una editorial con el mismo nombre",
			"event": [
				{
					"listen": "test",
					"script": {
						"exec": [
							"tests[\"No crea con el mismo nombre\"] = responseCode.code === 412;",
							"tests[\"Mensaje correcto de error\"] = responseBody.has(\"Editorial name already exists\");"
						],
						"type": "text/javascript"
					}
				}
			],
			"request": {
				"method": "POST",
				"header": [
					{
						"key": "Content-Type",
						"value": "application/json"
					}
				],
				"body": {
					"mode": "raw",
					"raw": "{\n    \"name\": \"Norma\"\n}"
				},
				"url": {
					"raw": "{{baseUrl}}/editorials",
					"host": [
						"{{baseUrl}}"
					],
					"path": [
						"editorials"
					]
				},
				"description": "**Release: Paso-5**\r\n\r\nCrea una nueva editorial pero con un nombre que ya existe. Verifica que se genera el error y el mensaje \"Ya existe una Editorial con el nombre\".\r\n\r\n**Código HTTP esperado: 412 Precondition failed\".**"
			},
			"response": []
		},
		{
			"name": "Crear un libro",
			"event": [
				{
					"listen": "test",
					"script": {
						"exec": [
							"var data = JSON.parse(responseBody);",
							"postman.setGlobalVariable(\"book_id\",data.id);",
							"tests[\"no genera error en el Post\"] = responseCode.code === 201;"
						],
						"type": "text/javascript"
					}
				}
			],
			"request": {
				"method": "POST",
				"header": [
					{
						"key": "Content-Type",
						"value": "application/json"
					}
				],
				"body": {
					"mode": "raw",
					"raw": "{\n    \"description\": \"Jorge Fondebrider traza un mundo fantastico con mapas de la geografia real y de sus mitologias, observando a los hombres lobo que han vivido en la imaginacion de Europa y America.\",\n    \"image\": \"https://static.iris.net.co/arcadia/upload/images/2017/7/31/64899_1.jpg\",\n    \"isbn\": \"930330149-8\",\n    \"editorial\": {\n        \"id\": {{editorial_id_1}}\n    },\n    \"name\": \"Historia de los hombres lobo 2\",\n    \"publishingDate\": \"2000-08-20T00:00:00-05:00\"\n}"
				},
				"url": {
					"raw": "{{baseUrl}}/books",
					"host": [
						"{{baseUrl}}"
					],
					"path": [
						"books"
					]
				},
				"description": "**Release: Paso-5**\r\n\r\nCrea un nuevo libro. El ISBN del recurso debe ser único. El Id es inicializado por la BD y se debe ver en la respuesta. \r\n\r\nPara la prueba, se guarda el id en una variable que será utilizada en otras peticiones de la colección.\r\n\r\n**Código http esperado: 200**"
			},
			"response": []
		},
		{
			"name": "Editar una editorial",
			"event": [
				{
					"listen": "test",
					"script": {
						"exec": [
							"console.log(responseBody);",
							"var data = JSON.parse(responseBody);",
							"tests[\"No genera error en el Put\"] = responseCode.code === 200;"
						],
						"type": "text/javascript"
					}
				}
			],
			"request": {
				"method": "PUT",
				"header": [
					{
						"key": "Content-Type",
						"value": "application/json"
					}
				],
				"body": {
					"mode": "raw",
					"raw": "{\n    \"name\": \"Editorial con nuevo nombre\"\n}"
				},
				"url": {
					"raw": "{{baseUrl}}/editorials/{{editorial_id_1}}",
					"host": [
						"{{baseUrl}}"
					],
					"path": [
						"editorials",
						"{{editorial_id_1}}"
					]
				},
				"description": "**Release: Paso-5**\r\n\r\nActualiza una editorial existente. El recurso solo tiene de atributo \"name\" que debe ser único. se envía el Id en la URL de la petición.\r\n\r\n**Código http esperado: 200**"
			},
			"response": []
		},
		{
			"name": "Editar una editorial que no existe",
			"event": [
				{
					"listen": "test",
					"script": {
						"exec": [
							"tests[\"No actualiza con id que no existe\"] = responseCode.code === 404;",
							"tests[\"Mensaje correcto de error\"] = responseBody.has(\"The editorial with the given id was not found\");"
						],
						"type": "text/javascript"
					}
				}
			],
			"request": {
				"method": "PUT",
				"header": [
					{
						"key": "Content-Type",
						"value": "application/json"
					}
				],
				"body": {
					"mode": "raw",
					"raw": "{\n    \"name\": \"Editorial con nuevo nombre\"\n}"
				},
				"url": {
					"raw": "{{baseUrl}}/editorials/0",
					"host": [
						"{{baseUrl}}"
					],
					"path": [
						"editorials",
						"0"
					]
				},
				"description": "**Release: Paso-5**\r\n\r\nActualiza una editorial que no existe. \r\n\r\nPara la prueba se verifica que se genera el error y el mensaje \"El recurso /editorials/0 no existe.\".\r\n\r\n**Código HTTP esperado: 404**"
			},
			"response": []
		},
		{
			"name": "Obtener todas las editoriales",
			"event": [
				{
					"listen": "test",
					"script": {
						"exec": [
							"var data= JSON.parse(responseBody);",
							"tests[\"No genera error en el Get all\"] = responseCode.code === 200;",
							"tests[\"editorials count\"] = data.length > 1;"
						],
						"type": "text/javascript"
					}
				}
			],
			"request": {
				"method": "GET",
				"header": [],
				"url": {
					"raw": "{{baseUrl}}/editorials/",
					"host": [
						"{{baseUrl}}"
					],
					"path": [
						"editorials",
						""
					]
				},
				"description": "**Release: Paso-5**\r\n\r\nConsulta todas las editoriales de la aplicación. \r\nLa petición no tiene cuerpo.\r\n\r\nPara la prueba, se verifica que el conjunto de editoriales en la respuesta tenga mas de una.\r\n\r\n**Código http esperado: 200**"
			},
			"response": []
		},
		{
			"name": "Obtener una editorial",
			"event": [
				{
					"listen": "test",
					"script": {
						"exec": [
							"console.log(responseBody);",
							"var data = JSON.parse(responseBody);",
							"tests[\"No genera error en el Get\"] = responseCode.code === 200;"
						],
						"type": "text/javascript"
					}
				}
			],
			"request": {
				"method": "GET",
				"header": [],
				"url": {
					"raw": "{{baseUrl}}/editorials/{{editorial_id_1}}",
					"host": [
						"{{baseUrl}}"
					],
					"path": [
						"editorials",
						"{{editorial_id_1}}"
					]
				},
				"description": "**Release: Paso-5**\r\n\r\nConsulta una editorial de la aplicación.  \r\nLa petición no tiene cuerpo.\r\nSe envía el id de la editorial deseada por la URL de la petición.\r\n\r\n**Código http esperado: 200**"
			},
			"response": []
		},
		{
			"name": "Obtener una editorial que no existe",
			"event": [
				{
					"listen": "test",
					"script": {
						"exec": [
							"tests[\"No consulta con id que no existe\"] = responseCode.code === 404;",
							"tests[\"Mensaje correcto de error\"] = responseBody.has(\"The editorial with the given id was not found\");"
						],
						"type": "text/javascript"
					}
				}
			],
			"request": {
				"method": "GET",
				"header": [],
				"url": {
					"raw": "{{baseUrl}}/editorials/0",
					"host": [
						"{{baseUrl}}"
					],
					"path": [
						"editorials",
						"0"
					]
				},
				"description": "**Release: Paso-5**\r\n\r\nConsulta una editorial que no existe en la aplicación.  \r\n\r\nPara la prueba se verifica que se genera el error y el mensaje \"El recurso /editorials/0 no existe.\".\r\n\r\n**Código http esperado: 404**"
			},
			"response": []
		},
		{
			"name": "Borrar una editorial con libros",
			"event": [
				{
					"listen": "test",
					"script": {
						"exec": [
							"tests[\"No borra con libros asociados\"] = responseCode.code === 412;"
						],
						"type": "text/javascript"
					}
				}
			],
			"request": {
				"method": "DELETE",
				"header": [],
				"body": {
					"mode": "raw",
					"raw": ""
				},
				"url": {
					"raw": "{{baseUrl}}/editorials/{{editorial_id_1}}",
					"host": [
						"{{baseUrl}}"
					],
					"path": [
						"editorials",
						"{{editorial_id_1}}"
					]
				},
				"description": "**Release: Paso-5**\r\n\r\nBorra una editorial existente pero con libros asociados. Verifica que se genera el error.\r\n\r\n**Código HTTP esperado: 412 Precondition failed\".**"
			},
			"response": []
		},
		{
			"name": "Borrar un libro",
			"event": [
				{
					"listen": "test",
					"script": {
						"exec": [
							"tests[\"No genera error en el Delete\"] = responseCode.code === 204;"
						],
						"type": "text/javascript"
					}
				}
			],
			"request": {
				"method": "DELETE",
				"header": [],
				"body": {
					"mode": "raw",
					"raw": ""
				},
				"url": {
					"raw": "{{baseUrl}}/books/{{book_id}}",
					"host": [
						"{{baseUrl}}"
					],
					"path": [
						"books",
						"{{book_id}}"
					]
				},
				"description": "**Release: Paso-5**\n\nBorra un libro. Se envía el id del libro creado anteriormente.\n\n**Código HTTP esperado: 204**"
			},
			"response": []
		},
		{
			"name": "Borrar una editorial",
			"event": [
				{
					"listen": "test",
					"script": {
						"exec": [
							"tests[\"No genera error en el Delete\"] = responseCode.code === 204;"
						],
						"type": "text/javascript"
					}
				}
			],
			"request": {
				"method": "DELETE",
				"header": [],
				"body": {
					"mode": "raw",
					"raw": ""
				},
				"url": {
					"raw": "{{baseUrl}}/editorials/{{editorial_id_1}}",
					"host": [
						"{{baseUrl}}"
					],
					"path": [
						"editorials",
						"{{editorial_id_1}}"
					]
				},
				"description": "**Release: Paso-5**\n\nBorra una editorial. Se envía el id de la entidad creada anteriormente.\n\n**Código HTTP esperado: 204**"
			},
			"response": []
		},
		{
			"name": "Borrar una editorial 2",
			"event": [
				{
					"listen": "test",
					"script": {
						"exec": [
							"tests[\"No genera error en el Delete\"] = responseCode.code === 204;"
						],
						"type": "text/javascript"
					}
				}
			],
			"request": {
				"method": "DELETE",
				"header": [],
				"body": {
					"mode": "raw",
					"raw": ""
				},
				"url": {
					"raw": "{{baseUrl}}/editorials/{{editorial_id_2}}",
					"host": [
						"{{baseUrl}}"
					],
					"path": [
						"editorials",
						"{{editorial_id_2}}"
					]
				},
				"description": "**Release: Paso-5**\n\nBorra una editorial. Se envía el id de la entidad creada anteriormente.\n\n**Código HTTP esperado: 204**"
			},
			"response": []
		},
		{
			"name": "Borrar una editorial que no existe",
			"event": [
				{
					"listen": "test",
					"script": {
						"exec": [
							"tests[\"No borra con id que no existe\"] = responseCode.code === 404;",
							"tests[\"Mensaje correcto de error\"] = responseBody.has(\"The editorial with the given id was not found\");"
						],
						"type": "text/javascript"
					}
				}
			],
			"request": {
				"method": "DELETE",
				"header": [],
				"body": {
					"mode": "raw",
					"raw": ""
				},
				"url": {
					"raw": "{{baseUrl}}/editorials/0",
					"host": [
						"{{baseUrl}}"
					],
					"path": [
						"editorials",
						"0"
					]
				},
				"description": "**Release: Paso-5**\r\n\r\nBorra una editorial que no existe en la aplicación.  \r\n\r\nPara la prueba se verifica que se genera el error y el mensaje \"El recurso /editorials/0 no existe.\".\r\n\r\n**Código http esperado: 404**"
			},
			"response": []
		}
	],
	"event": [
		{
			"listen": "prerequest",
			"script": {
				"type": "text/javascript",
				"exec": [
					""
				]
			}
		},
		{
			"listen": "test",
			"script": {
				"type": "text/javascript",
				"exec": [
					""
				]
			}
		}
	]
}